palimpzest/__init__.py
palimpzest/constants.py
palimpzest/policy.py
palimpzest/agents/__init__.py
palimpzest/agents/compute_agents.py
palimpzest/agents/search_agents.py
palimpzest/core/__init__.py
palimpzest/core/models.py
palimpzest/core/data/__init__.py
palimpzest/core/data/context.py
palimpzest/core/data/context_manager.py
palimpzest/core/data/dataset.py
palimpzest/core/data/index_dataset.py
palimpzest/core/data/iter_dataset.py
palimpzest/core/elements/__init__.py
palimpzest/core/elements/filters.py
palimpzest/core/elements/groupbysig.py
palimpzest/core/elements/records.py
palimpzest/core/lib/__init__.py
palimpzest/core/lib/schemas.py
palimpzest/prompts/__init__.py
palimpzest/prompts/agent_prompts.py
palimpzest/prompts/aggregate_prompts.py
palimpzest/prompts/context_search.py
palimpzest/prompts/convert_prompts.py
palimpzest/prompts/critique_and_refine_prompts.py
palimpzest/prompts/filter_prompts.py
palimpzest/prompts/join_prompts.py
palimpzest/prompts/moa_aggregator_prompts.py
palimpzest/prompts/moa_proposer_prompts.py
palimpzest/prompts/prompt_factory.py
palimpzest/prompts/split_merge_prompts.py
palimpzest/prompts/split_proposer_prompts.py
palimpzest/prompts/utils.py
palimpzest/prompts/validator.py
palimpzest/query/__init__.py
palimpzest/query/execution/__init__.py
palimpzest/query/execution/all_sample_execution_strategy.py
palimpzest/query/execution/execution_strategy.py
palimpzest/query/execution/execution_strategy_type.py
palimpzest/query/execution/mab_execution_strategy.py
palimpzest/query/execution/parallel_execution_strategy.py
palimpzest/query/execution/single_threaded_execution_strategy.py
palimpzest/query/generators/__init__.py
palimpzest/query/generators/generators.py
palimpzest/query/operators/__init__.py
palimpzest/query/operators/aggregate.py
palimpzest/query/operators/compute.py
palimpzest/query/operators/convert.py
palimpzest/query/operators/critique_and_refine.py
palimpzest/query/operators/distinct.py
palimpzest/query/operators/filter.py
palimpzest-1.3.1.dist-info/licenses/LICENSE
palimpzest-1.3.1.dist-info/METADATA
palimpzest-1.3.1.dist-info/WHEEL
palimpzest-1.3.1.dist-info/top_level.txt
palimpzest-1.3.1.dist-info/RECORD
