Metadata-Version: 2.4
Name: palimpzest
Version: 1.3.1
Summary: Palimpzest is a system which enables anyone to process AI-powered analytical queries simply by defining them in a declarative language
Author-email: MIT DSG Semantic Management Lab <michjc@csail.mit.edu>
Project-URL: homepage, https://palimpzest.org
Project-URL: repository, https://github.com/mitdbg/palimpzest/
Project-URL: documentation, https://palimpzest.org
Keywords: relational,optimization,llm,AI programming,extraction,tools,document,search,integration
Classifier: Development Status :: 4 - Beta
Classifier: Intended Audience :: Developers
Classifier: License :: OSI Approved :: MIT License
Classifier: Programming Language :: Python :: 3
Classifier: Programming Language :: Python :: 3.8
Requires-Python: >=3.12
License-File: LICENSE
Requires-Dist: anthropic>=0.55.0
Requires-Dist: beautifulsoup4>=4.13.4
Requires-Dist: chromadb>=1.0.15
Requires-Dist: colorama>=0.4.6
Requires-Dist: datasets>=4.0.0
Requires-Dist: fastapi~=0.115.0
Requires-Dist: gradio>=5.26.0
Requires-Dist: litellm>=1.76.1
Requires-Dist: numpy==2.0.2
Requires-Dist: openai>=1.0
Requires-Dist: pandas>=2.1.1
Requires-Dist: pytest>=8.2.2
Requires-Dist: pillow>=11.3.0
Requires-Dist: prettytable>=3.9.0
Requires-Dist: psutil==5.9.5
Requires-Dist: PyLD>=2.0.4
Requires-Dist: pyarrow>=20.0.0
Requires-Dist: pypdf>=5.1.0
Requires-Dist: pytest-mock>=3.14.0
Requires-Dist: python-dotenv>=1.2.1
Requires-Dist: pyyaml>=6.0.1
Requires-Dist: requests>=2.25
Requires-Dist: ruff>=0.9.0
Requires-Dist: sentence-transformers==5.0.0
Requires-Dist: setuptools>=70.1.1
Requires-Dist: smolagents[toolkit]
Requires-Dist: tabulate>=0.9.0
Requires-Dist: together>=1.5.5
Requires-Dist: tqdm~=4.66.1
Requires-Dist: rich[jupyter]>=13.9.2
Provides-Extra: vllm
Requires-Dist: vllm>=0.10.1.1; extra == "vllm"
Dynamic: license-file
